signal_cli_jsonrpc/__init__.py
signal_cli_jsonrpc/rpc_command_outputs.py
signal_cli_jsonrpc/rpc_commands.py
signal_cli_jsonrpc/rpc_session.py
signal_cli_jsonrpc/rpc_types.py
signal_cli_jsonrpc/utils.py
signal_cli_jsonrpc-0.13.20.dev1.dist-info/WHEEL
signal_cli_jsonrpc-0.13.20.dev1.dist-info/METADATA
signal_cli_jsonrpc-0.13.20.dev1.dist-info/RECORD
