Metadata-Version: 2.3
Name: signal-cli-jsonrpc
Version: 0.13.20.dev1
Summary: Strongly typed Python dataclass interface to signal-cli's RPC commands
Requires-Dist: aiohttp>=3.12.13
Requires-Dist: aiohttp-sse-client>=0.2.1
Requires-Dist: caseutil>=0.7.2
Requires-Dist: dacite>=1.9.2
Requires-Python: >=3.14
